{
  "family": "translation-backend",
  "networkMode": "awsvpc",
  "requiresCompatibilities": ["FARGATE"],
  "cpu": "2048",
  "memory": "4096",
  "containerDefinitions": [
    {
      "name": "translation-backend",
      "image": "<AWS_ACCOUNT_ID>.dkr.ecr.<REGION>.amazonaws.com/translation-backend:latest",
      "essential": true,
      "portMappings": [
        {
          "containerPort": 8000,
          "protocol": "tcp"
        }
      ],
      "environment": [
        {
          "name": "PORT",
          "value": "8000"
        },
        {
          "name": "HOST",
          "value": "0.0.0.0"
        },
        {
          "name": "CORS_ORIGINS",
          "value": "https://your-frontend-domain.com"
        },
        {
          "name": "MODEL_CACHE_DIR",
          "value": "/app/models"
        }
      ],
      "logConfiguration": {
        "logDriver": "awslogs",
        "options": {
          "awslogs-group": "/ecs/translation-backend",
          "awslogs-region": "<REGION>",
          "awslogs-stream-prefix": "ecs"
        }
      },
      "healthCheck": {
        "command": ["CMD-SHELL", "curl -f http://localhost:8000/health || exit 1"],
        "interval": 30,
        "timeout": 5,
        "retries": 3,
        "startPeriod": 60
      }
    }
  ]
}
